lob_python/__init__.py
lob_python/api_client.py
lob_python/configuration.py
lob_python/exceptions.py
lob_python/model_utils.py
lob_python/rest.py
lob_python/api/__init__.py
lob_python/api/addresses_api.py
lob_python/api/bank_accounts_api.py
lob_python/api/billing_groups_api.py
lob_python/api/buckslip_orders_api.py
lob_python/api/buckslips_api.py
lob_python/api/card_orders_api.py
lob_python/api/cards_api.py
lob_python/api/checks_api.py
lob_python/api/default_api.py
lob_python/api/identity_validation_api.py
lob_python/api/intl_autocompletions_api.py
lob_python/api/intl_verifications_api.py
lob_python/api/letters_api.py
lob_python/api/postcards_api.py
lob_python/api/reverse_geocode_lookups_api.py
lob_python/api/self_mailers_api.py
lob_python/api/template_versions_api.py
lob_python/api/templates_api.py
lob_python/api/us_autocompletions_api.py
lob_python/api/us_verifications_api.py
lob_python/api/zip_lookups_api.py
lob_python/apis/__init__.py
lob_python/model/__init__.py
lob_python/model/address.py
lob_python/model/address_deletion.py
lob_python/model/address_domestic.py
lob_python/model/address_domestic_expanded.py
lob_python/model/address_editable.py
lob_python/model/address_list.py
lob_python/model/adr_id.py
lob_python/model/bank_account.py
lob_python/model/bank_account_deletion.py
lob_python/model/bank_account_list.py
lob_python/model/bank_account_verify.py
lob_python/model/bank_account_writable.py
lob_python/model/bank_id.py
lob_python/model/bank_type_enum.py
lob_python/model/bg_description.py
lob_python/model/bg_id.py
lob_python/model/billing_group.py
lob_python/model/billing_group_editable.py
lob_python/model/billing_group_list.py
lob_python/model/bo_id.py
lob_python/model/buckslip.py
lob_python/model/buckslip_deletion.py
lob_python/model/buckslip_description.py
lob_python/model/buckslip_editable.py
lob_python/model/buckslip_id.py
lob_python/model/buckslip_order.py
lob_python/model/buckslip_order_editable.py
lob_python/model/buckslip_orders_list.py
lob_python-5.0.2.dist-info/METADATA
lob_python-5.0.2.dist-info/WHEEL
lob_python-5.0.2.dist-info/top_level.txt
lob_python-5.0.2.dist-info/RECORD
