Metadata-Version: 2.1
Name: lob-python
Version: 5.0.2
Summary: Lob
Home-page: https://github.com/lob/lob-python
Author: Lob Developer Experience
Author-email: lob-openapi@lob.com
License: MIT
Keywords: OpenAPI,OpenAPI-Generator,Lob
Requires-Dist: urllib3 (>=1.25.3)
Requires-Dist: python-dateutil
